rosutils/__init__.py
rosutils/__main__.py
rosutils-0.0.20.dist-info/METADATA
rosutils-0.0.20.dist-info/WHEEL
rosutils-0.0.20.dist-info/entry_points.txt
rosutils-0.0.20.dist-info/top_level.txt
rosutils-0.0.20.dist-info/RECORD
